AUTHORS.rst
CONTRIBUTING.rst
HISTORY.rst
LICENSE
MANIFEST.in
README.rst
setup.cfg
setup.py
docs/Makefile
docs/authors.rst
docs/conf.py
docs/contributing.rst
docs/history.rst
docs/index.rst
docs/installation.rst
docs/make.bat
docs/modules.rst
docs/mona_foo.rst
docs/readme.rst
docs/usage.rst
docs/_build/html/_static/ajax-loader.gif
docs/_build/html/_static/comment-bright.png
docs/_build/html/_static/comment-close.png
docs/_build/html/_static/comment.png
docs/_build/html/_static/down-pressed.png
docs/_build/html/_static/down.png
docs/_build/html/_static/file.png
docs/_build/html/_static/minus.png
docs/_build/html/_static/plus.png
docs/_build/html/_static/up-pressed.png
docs/_build/html/_static/up.png
mona_foo/__init__.py
mona_foo/cli.py
mona_foo/mona_foo.py
mona_foo.egg-info/PKG-INFO
mona_foo.egg-info/SOURCES.txt
mona_foo.egg-info/dependency_links.txt
mona_foo.egg-info/entry_points.txt
mona_foo.egg-info/not-zip-safe
mona_foo.egg-info/requires.txt
mona_foo.egg-info/top_level.txt
tests/test_mona_foo.py