Metadata-Version: 1.1
Name: mona-foo
Version: 0.1.0
Summary: my first useless python package
Home-page: https://github.com/monaw/mona_foo
Author: Mona Wong
Author-email: mona@sdsc.edu
License: MIT license
Keywords: mona_foo
Platform: UNKNOWN
Classifier: Development Status :: 2 - Pre-Alpha
Classifier: Intended Audience :: Developers
Classifier: License :: OSI Approved :: MIT License
Classifier: Natural Language :: English
Classifier: Programming Language :: Python :: 2
Classifier: Programming Language :: Python :: 2.7
Classifier: Programming Language :: Python :: 3
Classifier: Programming Language :: Python :: 3.4
Classifier: Programming Language :: Python :: 3.5
Classifier: Programming Language :: Python :: 3.6
Classifier: Programming Language :: Python :: 3.7
